{
    "key": "group_6149f12ee6a44",
    "title": "Block: CTA E-tjänster + text",
    "fields": [
        {
            "key": "field_61694424dc1db",
            "label": "Bakgrundsfärg",
            "name": "block_background",
            "type": "button_group",
            "instructions": "Default vit.",
            "required": 1,
            "conditional_logic": 0,
            "wrapper": {
                "width": "",
                "class": "",
                "id": ""
            },
            "choices": {
                "white": "Vit",
                "gray": "Grå"
            },
            "allow_null": 0,
            "default_value": "white",
            "layout": "horizontal",
            "return_format": "value"
        },
        {
            "key": "field_616944d1dc1dd",
            "label": "Dekoration",
            "name": "block_decorations",
            "type": "button_group",
            "instructions": "Välj dekoration, alternativ 1, 2 eller Ej dekoration\r\nAlt 1. Orange vänster, blåa till höger\r\nalt 2: Två blåa till höger",
            "required": 0,
            "conditional_logic": 0,
            "wrapper": {
                "width": "",
                "class": "",
                "id": ""
            },
            "choices": {
                "alt1": "Alt. 1",
                "alt2": "Alt. 2",
                "alt3": "Ej dekoration"
            },
            "allow_null": 0,
            "default_value": 0,
            "layout": "horizontal",
            "return_format": "value"
        },
        {
            "key": "field_61694496dc1dc",
            "label": "Position av block",
            "name": "block_align",
            "type": "button_group",
            "instructions": "",
            "required": 0,
            "conditional_logic": 0,
            "wrapper": {
                "width": "",
                "class": "",
                "id": ""
            },
            "choices": {
                "left": "Vänster",
                "center": "Center"
            },
            "allow_null": 0,
            "default_value": "center",
            "layout": "horizontal",
            "return_format": "value"
        },
        {
            "key": "field_6149f12f01c41",
            "label": "Titel",
            "name": "title",
            "type": "text",
            "instructions": "",
            "required": 0,
            "conditional_logic": 0,
            "wrapper": {
                "width": "",
                "class": "",
                "id": ""
            },
            "default_value": "Det är enkelt att ändra betalsätt",
            "placeholder": "",
            "prepend": "",
            "append": "",
            "maxlength": ""
        },
        {
            "key": "field_6149f12f01c8f",
            "label": "Brödtext",
            "name": "bread_text",
            "type": "wysiwyg",
            "instructions": "",
            "required": 0,
            "conditional_logic": 0,
            "wrapper": {
                "width": "",
                "class": "",
                "id": ""
            },
            "default_value": "",
            "tabs": "all",
            "toolbar": "full",
            "media_upload": 1,
            "delay": 0
        }
    ],
    "location": [
        [
            {
                "param": "block",
                "operator": "==",
                "value": "acf\/cta-e-tjanster"
            }
        ]
    ],
    "menu_order": 0,
    "position": "normal",
    "style": "default",
    "label_placement": "top",
    "instruction_placement": "label",
    "hide_on_screen": "",
    "active": true,
    "description": "",
    "show_in_rest": 0,
    "modified": 1644417883
}